balistica/IntegratedBallisticsSuite.py
balistica/__init__.py
balistica/__main__.py
balistica/GUI/AnalyticV.py
balistica/GUI/Ideal.py
balistica/GUI/NumericalCombined.py
balistica/GUI/NumericalThermoFluid.py
balistica/GUI/NumericalV.py
balistica/GUI/NumericalV2.py
balistica/GUI/NumericalV2Wind.py
balistica/GUI/NumericalVGrav.py
balistica/GUI/NumericalVWind.py
balistica/GUI/__init__.py
balistica/PhysicsEngine/AnalyticVPhysicsHandler.py
balistica/PhysicsEngine/IdealPhysicsHandler.py
balistica/PhysicsEngine/NumericalCombinedHandler.py
balistica/PhysicsEngine/NumericalThermoFluidHandler.py
balistica/PhysicsEngine/NumericalVGravPhysicsHandler.py
balistica/PhysicsEngine/NumericalVPhysicsHandler.py
balistica/PhysicsEngine/NumericalVSqPhysicsHandler.py
balistica/PhysicsEngine/NumericalVSqWindPhysicsHandler.py
balistica/PhysicsEngine/NumericalVWindPhysicsHandler.py
balistica/PhysicsEngine/PhysicsHandler.py
balistica/PhysicsEngine/__init__.py
BALISTICA-1.0.0.dist-info/LICENSE
BALISTICA-1.0.0.dist-info/METADATA
BALISTICA-1.0.0.dist-info/WHEEL
BALISTICA-1.0.0.dist-info/entry_points.txt
BALISTICA-1.0.0.dist-info/top_level.txt
BALISTICA-1.0.0.dist-info/RECORD
